ezrepl/Completer.py
ezrepl/HelpMenu.py
ezrepl/Repl.py
ezrepl/__init__.py
ezrepl/errors/__init__.py
ezrepl-1.1.dist-info/LICENSE
ezrepl-1.1.dist-info/METADATA
ezrepl-1.1.dist-info/WHEEL
ezrepl-1.1.dist-info/top_level.txt
ezrepl-1.1.dist-info/RECORD
