Metadata-Version: 2.1
Name: ezrepl
Version: 1.1
Summary: A python package for making simple repls
Home-page: https://github.com/wastella/ezrepl
Author: William Stella
Author-email: william.a.stella@gmail.com
License: UNKNOWN
Platform: UNKNOWN
Classifier: Programming Language :: Python :: 3
Classifier: License :: OSI Approved :: MIT License
Classifier: Operating System :: OS Independent
Requires-Python: >=3.6
